{
  "last_update": "2025-10-08",
  "stocks": {
    "6770": {
      "stock_name": "力積電",
      "momentum": 17.71653569914653,
      "days": 8,
      "last_signal_date": "2025-10-07"
    },
    "3231": {
      "stock_name": "緯創",
      "momentum": 11.032028469750887,
      "days": 6,
      "last_signal_date": "2025-10-07"
    },
    "8021": {
      "stock_name": "尖點",
      "momentum": 15.841584158415834,
      "days": 6,
      "last_signal_date": "2025-10-07"
    },
    "9910": {
      "stock_name": "豐泰",
      "momentum": 8.130081300813007,
      "days": 6,
      "last_signal_date": "2025-10-07"
    },
    "1504": {
      "stock_name": "東元",
      "momentum": 18.822294230372584,
      "days": 5,
      "last_signal_date": "2025-10-07"
    },
    "8996": {
      "stock_name": "高力",
      "momentum": 23.298033282904697,
      "days": 5,
      "last_signal_date": "2025-10-07"
    },
    "2344": {
      "stock_name": "華邦電",
      "momentum": 25.256982324563417,
      "days": 4,
      "last_signal_date": "2025-10-07"
    },
    "3017": {
      "stock_name": "奇鋐",
      "momentum": 17.227319062181444,
      "days": 4,
      "last_signal_date": "2025-10-07"
    },
    "6449": {
      "stock_name": "鈺邦",
      "momentum": 11.794871794871797,
      "days": 4,
      "last_signal_date": "2025-10-07"
    },
    "6531": {
      "stock_name": "愛普*",
      "momentum": 16.886930983847282,
      "days": 4,
      "last_signal_date": "2025-10-07"
    },
    "6768": {
      "stock_name": "志強-KY",
      "momentum": 14.705882352941169,
      "days": 4,
      "last_signal_date": "2025-10-07"
    },
    "8110": {
      "stock_name": "華東",
      "momentum": 29.72222434149847,
      "days": 4,
      "last_signal_date": "2025-10-07"
    },
    "1590": {
      "stock_name": "亞德客-KY",
      "momentum": 12.084993359893748,
      "days": 3,
      "last_signal_date": "2025-10-07"
    },
    "1727": {
      "stock_name": "中華化",
      "momentum": 13.239438768843526,
      "days": 3,
      "last_signal_date": "2025-10-07"
    },
    "2308": {
      "stock_name": "台達電",
      "momentum": 15.573770491803284,
      "days": 3,
      "last_signal_date": "2025-10-07"
    },
    "2330": {
      "stock_name": "台積電",
      "momentum": 9.961685823754785,
      "days": 3,
      "last_signal_date": "2025-10-07"
    },
    "2360": {
      "stock_name": "致茂",
      "momentum": 11.917098445595853,
      "days": 3,
      "last_signal_date": "2025-10-07"
    },
    "2408": {
      "stock_name": "南亞科",
      "momentum": 24.931502668824912,
      "days": 3,
      "last_signal_date": "2025-10-07"
    },
    "2451": {
      "stock_name": "創見",
      "momentum": 7.727272727272738,
      "days": 3,
      "last_signal_date": "2025-10-07"
    },
    "3006": {
      "stock_name": "晶豪科",
      "momentum": 18.767119107181074,
      "days": 3,
      "last_signal_date": "2025-10-07"
    },
    "3715": {
      "stock_name": "定穎投控",
      "momentum": 9.060400823121206,
      "days": 3,
      "last_signal_date": "2025-10-07"
    },
    "4551": {
      "stock_name": "智伸科",
      "momentum": 7.86516853932584,
      "days": 3,
      "last_signal_date": "2025-10-07"
    },
    "4967": {
      "stock_name": "十銓",
      "momentum": 15.415842728054985,
      "days": 3,
      "last_signal_date": "2025-10-07"
    },
    "4989": {
      "stock_name": "榮科",
      "momentum": 25.631062035421714,
      "days": 3,
      "last_signal_date": "2025-10-07"
    },
    "6139": {
      "stock_name": "亞翔",
      "momentum": 8.774373259052926,
      "days": 3,
      "last_signal_date": "2025-10-07"
    },
    "6209": {
      "stock_name": "今國光",
      "momentum": 13.774836458117768,
      "days": 3,
      "last_signal_date": "2025-10-07"
    },
    "6235": {
      "stock_name": "華孚",
      "momentum": 14.84375,
      "days": 3,
      "last_signal_date": "2025-10-07"
    },
    "6239": {
      "stock_name": "力成",
      "momentum": 8.219178082191792,
      "days": 3,
      "last_signal_date": "2025-10-07"
    },
    "6442": {
      "stock_name": "光聖",
      "momentum": 10.718789407313988,
      "days": 3,
      "last_signal_date": "2025-10-07"
    },
    "6446": {
      "stock_name": "藥華藥",
      "momentum": 7.5728155339805925,
      "days": 3,
      "last_signal_date": "2025-10-07"
    },
    "6805": {
      "stock_name": "富世達",
      "momentum": 12.449799196787147,
      "days": 3,
      "last_signal_date": "2025-10-07"
    },
    "8046": {
      "stock_name": "南電",
      "momentum": 11.946902654867264,
      "days": 3,
      "last_signal_date": "2025-10-07"
    },
    "8070": {
      "stock_name": "長華*",
      "momentum": 9.912172933970421,
      "days": 3,
      "last_signal_date": "2025-10-07"
    },
    "1616": {
      "stock_name": "億泰",
      "momentum": 7.449852035660087,
      "days": 1,
      "last_signal_date": "2025-10-07"
    },
    "1786": {
      "stock_name": "科妍",
      "momentum": 8.866995073891616,
      "days": 1,
      "last_signal_date": "2025-10-07"
    },
    "1795": {
      "stock_name": "美時",
      "momentum": 7.129094412331405,
      "days": 1,
      "last_signal_date": "2025-10-07"
    },
    "1802": {
      "stock_name": "台玻",
      "momentum": 11.496349132793293,
      "days": 1,
      "last_signal_date": "2025-10-07"
    },
    "2024": {
      "stock_name": "志聯",
      "momentum": 13.772449892126314,
      "days": 1,
      "last_signal_date": "2025-10-07"
    },
    "2313": {
      "stock_name": "華通",
      "momentum": 10.217983438809197,
      "days": 1,
      "last_signal_date": "2025-10-07"
    },
    "2327": {
      "stock_name": "國巨*",
      "momentum": 8.529411764705873,
      "days": 1,
      "last_signal_date": "2025-10-07"
    },
    "2337": {
      "stock_name": "旺宏",
      "momentum": 8.183637552276956,
      "days": 1,
      "last_signal_date": "2025-10-07"
    },
    "2399": {
      "stock_name": "映泰",
      "momentum": 9.162303481929769,
      "days": 1,
      "last_signal_date": "2025-10-07"
    },
    "3008": {
      "stock_name": "大立光",
      "momentum": 7.021276595744674,
      "days": 1,
      "last_signal_date": "2025-10-07"
    },
    "3149": {
      "stock_name": "正達",
      "momentum": 7.5812312484214495,
      "days": 1,
      "last_signal_date": "2025-10-07"
    },
    "3413": {
      "stock_name": "京鼎",
      "momentum": 11.940298507462677,
      "days": 1,
      "last_signal_date": "2025-10-07"
    },
    "6862": {
      "stock_name": "三集瑞-KY",
      "momentum": 8.333333333333325,
      "days": 1,
      "last_signal_date": "2025-10-07"
    }
  }
}